catoml/__init__.py
catoml-0.1.2.dist-info/METADATA
catoml-0.1.2.dist-info/WHEEL
catoml-0.1.2.dist-info/RECORD
